src/__init__.py
src/config.py
src/main.py
src/mcp_server.py
src/api/__init__.py
src/api/routes.py
src/audio/__init__.py
src/audio/player.py
src/tts/__init__.py
src/tts/manager.py
src/tts/providers/__init__.py
src/tts/providers/base.py
src/tts/providers/elevenlabs.py
src/tts/providers/openai_fm.py
mcp_tts-0.3.0.dist-info/METADATA
mcp_tts-0.3.0.dist-info/WHEEL
mcp_tts-0.3.0.dist-info/entry_points.txt
mcp_tts-0.3.0.dist-info/licenses/LICENSE
mcp_tts-0.3.0.dist-info/RECORD
