Metadata-Version: 2.4
Name: mcp-tts
Version: 0.3.0
Summary: MCP Text-to-Speech Server for Cursor IDE (and others) with cross-platform audio playback
Project-URL: Homepage, https://github.com/EnviralDesign/mcp-tts
Project-URL: Repository, https://github.com/EnviralDesign/mcp-tts
Project-URL: Issues, https://github.com/EnviralDesign/mcp-tts/issues
Author-email: Lucas Morgan <enviraldesign@gmail.com>
License: MIT
License-File: LICENSE
Keywords: cursor,ide,mcp,text-to-speech,tts
Classifier: Development Status :: 4 - Beta
Classifier: Intended Audience :: Developers
Classifier: License :: OSI Approved :: MIT License
Classifier: Programming Language :: Python :: 3
Classifier: Programming Language :: Python :: 3.11
Classifier: Programming Language :: Python :: 3.12
Classifier: Topic :: Multimedia :: Sound/Audio :: Speech
Classifier: Topic :: Software Development
Requires-Python: >=3.11
Requires-Dist: elevenlabs>=1.5.0
Requires-Dist: fastapi>=0.104.0
Requires-Dist: httpx>=0.25.0
Requires-Dist: mcp>=0.6.0
Requires-Dist: numpy>=1.24.0
Requires-Dist: openai>=1.5.0
Requires-Dist: pydantic>=2.5.0
Requires-Dist: python-dotenv>=1.0.0
Requires-Dist: python-multipart>=0.0.6
Requires-Dist: pyyaml>=6.0
Requires-Dist: sounddevice>=0.4.6
Requires-Dist: uvicorn[standard]>=0.24.0
Requires-Dist: websockets>=12.0
Provides-Extra: dev
Requires-Dist: black>=23.0.0; extra == 'dev'
Requires-Dist: ruff>=0.1.0; extra == 'dev'
